mpspy/__init__.py
mpspy/instance.py
mpspy/log.py
mpspy/reader.py
mpspy-0.1.4.dist-info/LICENSE
mpspy-0.1.4.dist-info/METADATA
mpspy-0.1.4.dist-info/WHEEL
mpspy-0.1.4.dist-info/RECORD
