Metadata-Version: 2.3
Name: mpspy
Version: 0.1.4
Summary: 
Author: Christoph Hansknecht
Author-email: christoph.hansknecht@tu-clausthal.de
Requires-Python: >=3.10
Classifier: Programming Language :: Python :: 3
Classifier: Programming Language :: Python :: 3.10
Classifier: Programming Language :: Python :: 3.11
Classifier: Programming Language :: Python :: 3.12
Classifier: Programming Language :: Python :: 3.13
Requires-Dist: numpy (>=2.0)
Requires-Dist: scipy (>=1.14)
